{"cameraMode":{"drawMode":0,"name":"Shaded","section":"Shading Mode"},"sceneLighting":true,"audioPlay":false,"sceneViewState":{"m_AlwaysRefresh":false,"showFog":true,"showSkybox":true,"showFlares":true,"showImageEffects":true,"showParticleSystems":true,"showVisualEffectGraphs":true,"m_FxEnabled":true},"in2DMode":false,"pivot":{"x":-3.8318488597869875,"y":-23.314672470092775,"z":-72.64747619628906},"rotation":{"x":-0.04690544307231903,"y":-0.9481498599052429,"z":0.2673347592353821,"w":-0.1665823757648468},"size":30.17276382446289,"orthographic":false}