{"cameraMode":{"drawMode":2,"name":"Shaded Wireframe","section":"Shading Mode"},"sceneLighting":true,"audioPlay":false,"sceneViewState":{"m_AlwaysRefresh":false,"showFog":true,"showSkybox":true,"showFlares":true,"showImageEffects":true,"showParticleSystems":true,"showVisualEffectGraphs":true,"m_FxEnabled":true},"in2DMode":false,"pivot":{"x":117.29691314697266,"y":18.38006019592285,"z":-121.18788146972656},"rotation":{"x":0.0649065151810646,"y":0.8160098195075989,"z":-0.09342819452285767,"w":0.5668691992759705},"size":56.050567626953128,"orthographic":false}